soccer_articles/__init__.py
soccer_articles/_bbc.py
soccer_articles/_reuters.py
soccer_articles/article.py
soccer_articles-0.1.5.dist-info/WHEEL
soccer_articles-0.1.5.dist-info/METADATA
soccer_articles-0.1.5.dist-info/RECORD
