Metadata-Version: 2.1
Name: soccer-articles
Version: 0.1.5
Summary: 
Author: keurcien
Author-email: keurcien@appchoose.io
Requires-Python: >=3.2,<4.0
Classifier: Programming Language :: Python :: 3
Classifier: Programming Language :: Python :: 3.10
Classifier: Programming Language :: Python :: 3.4
Classifier: Programming Language :: Python :: 3.5
Classifier: Programming Language :: Python :: 3.6
Classifier: Programming Language :: Python :: 3.7
Classifier: Programming Language :: Python :: 3.8
Classifier: Programming Language :: Python :: 3.9
Requires-Dist: beautifulsoup4 (==4.10.0)
